<annotation>
		<folder>folder</folder>
		<filename>blue_BR_doort_frame00714.jpg</filename>
		<source>
		<database>object_id</database>
	</source>
	<size>
		<width>640</width>
		<height>480</height>
		<depth>3</depth>
	</size>
	<segmented>0</segmented>
	<object>
		<name>Duckie</name>
		<pose>Unspecified</pose>
		<truncated>Unspecified</truncated>
		<difficult>0</difficult>
		<bndbox>
			<xmin>246</xmin>
			<ymin>167</ymin>
			<xmax>258</xmax>
			<ymax>178</ymax>
		</bndbox>
	</object>

	<object>
		<name>Duckie</name>
		<pose>Unspecified</pose>
		<truncated>Unspecified</truncated>
		<difficult>0</difficult>
		<bndbox>
			<xmin>316</xmin>
			<ymin>159</ymin>
			<xmax>331</xmax>
			<ymax>173</ymax>
		</bndbox>
	</object>

	<object>
		<name>Duckie</name>
		<pose>Unspecified</pose>
		<truncated>Unspecified</truncated>
		<difficult>0</difficult>
		<bndbox>
			<xmin>338</xmin>
			<ymin>159</ymin>
			<xmax>351</xmax>
			<ymax>177</ymax>
		</bndbox>
	</object>

	<object>
		<name>QR code</name>
		<pose>Unspecified</pose>
		<truncated>Unspecified</truncated>
		<difficult>0</difficult>
		<bndbox>
			<xmin>388</xmin>
			<ymin>150</ymin>
			<xmax>480</xmax>
			<ymax>281</ymax>
		</bndbox>
	</object>

	<object>
		<name>QR code</name>
		<pose>Unspecified</pose>
		<truncated>Unspecified</truncated>
		<difficult>0</difficult>
		<bndbox>
			<xmin>195</xmin>
			<ymin>151</ymin>
			<xmax>230</xmax>
			<ymax>180</ymax>
		</bndbox>
	</object>

	<object>
		<name>Intersection sign</name>
		<pose>Unspecified</pose>
		<truncated>Unspecified</truncated>
		<difficult>0</difficult>
		<bndbox>
			<xmin>380</xmin>
			<ymin>21</ymin>
			<xmax>475</xmax>
			<ymax>139</ymax>
		</bndbox>
	</object>

	<object>
		<name>Intersection sign</name>
		<pose>Unspecified</pose>
		<truncated>Unspecified</truncated>
		<difficult>0</difficult>
		<bndbox>
			<xmin>198</xmin>
			<ymin>120</ymin>
			<xmax>225</xmax>
			<ymax>146</ymax>
		</bndbox>
	</object>
</annotation>
